GApi4Term/__init__.py
GApi4Term/gapi.py
GApi4Term/commands/__init__.py
GApi4Term/commands/accounts.py
GApi4Term/commands/drive.py
GApi4Term/commands/email.py
GApi4Term/commands/googl.py
GApi4Term/commands/parser.py
GApi4Term/commands/tasks.py
GApi4Term/commands/utils.py
GApi4Term/core/__init__.py
GApi4Term/core/configstore.py
GApi4Term/core/drive.py
GApi4Term/core/gmail.py
GApi4Term/core/oauth.py
GApi4Term/core/tasks.py
GApi4Term/core/urlshortener.py
gapi4term-0.8.8.dist-info/DESCRIPTION.rst
gapi4term-0.8.8.dist-info/METADATA
gapi4term-0.8.8.dist-info/RECORD
gapi4term-0.8.8.dist-info/WHEEL
gapi4term-0.8.8.dist-info/entry_points.txt
gapi4term-0.8.8.dist-info/metadata.json
gapi4term-0.8.8.dist-info/top_level.txt
